<?xml version="1.0" encoding="UTF-8"?><record_update table="sp_container">
    <sp_container action="DELETE">
        <background_color/>
        <background_image/>
        <background_style>default</background_style>
        <bootstrap_alt>false</bootstrap_alt>
        <class_name/>
        <container_class_name/>
        <name>VCM Home Page - Container 2</name>
        <order>2</order>
        <sp_page display_value="vcm_home_page">8dbbe4b2db6caf40c203a2364b9619fe</sp_page>
        <subheader>false</subheader>
        <sys_class_name>sp_container</sys_class_name>
        <sys_created_by>Nehal.Ranpise@infocenter.io</sys_created_by>
        <sys_created_on>2018-09-18 07:47:14</sys_created_on>
        <sys_customer_update>false</sys_customer_update>
        <sys_id>b18178f6db6caf40c203a2364b961910</sys_id>
        <sys_mod_count>0</sys_mod_count>
        <sys_name>VCM Home Page - Container 2</sys_name>
        <sys_package display_value="Vendor Contract Management" source="x_icir_vcm">3fe81872db2caf40c203a2364b9619e0</sys_package>
        <sys_policy/>
        <sys_replace_on_upgrade>false</sys_replace_on_upgrade>
        <sys_scope display_value="Vendor Contract Management">3fe81872db2caf40c203a2364b9619e0</sys_scope>
        <sys_update_name>sp_container_b18178f6db6caf40c203a2364b961910</sys_update_name>
        <sys_updated_by>Nehal.Ranpise@infocenter.io</sys_updated_by>
        <sys_updated_on>2018-09-18 07:47:14</sys_updated_on>
        <title/>
        <width>container</width>
    </sp_container>
    <sys_update_version action="INSERT_OR_UPDATE">
        <action>DELETE</action>
        <application display_value="Vendor Contract Management">3fe81872db2caf40c203a2364b9619e0</application>
        <file_path/>
        <instance_id>978e28dadba5cf4060a6f0e5bf9619ae</instance_id>
        <instance_name>ven02229</instance_name>
        <name>sp_container_b18178f6db6caf40c203a2364b961910</name>
        <payload><![CDATA[<?xml version="1.0" encoding="UTF-8"?><record_update table="sp_container"><sp_container action="INSERT_OR_UPDATE"><background_color/><background_image/><background_style>default</background_style><bootstrap_alt>false</bootstrap_alt><class_name/><container_class_name/><name>VCM Home Page - Container 2</name><order>2</order><sp_page display_value="vcm_home_page">8dbbe4b2db6caf40c203a2364b9619fe</sp_page><subheader>false</subheader><sys_class_name>sp_container</sys_class_name><sys_created_by>Nehal.Ranpise@infocenter.io</sys_created_by><sys_created_on>2018-09-18 07:47:14</sys_created_on><sys_customer_update>false</sys_customer_update><sys_id>b18178f6db6caf40c203a2364b961910</sys_id><sys_mod_count>0</sys_mod_count><sys_name>VCM Home Page - Container 2</sys_name><sys_package display_value="Vendor Contract Management" source="x_icir_vcm">3fe81872db2caf40c203a2364b9619e0</sys_package><sys_policy/><sys_replace_on_upgrade>false</sys_replace_on_upgrade><sys_scope display_value="Vendor Contract Management">3fe81872db2caf40c203a2364b9619e0</sys_scope><sys_update_name>sp_container_b18178f6db6caf40c203a2364b961910</sys_update_name><sys_updated_by>Nehal.Ranpise@infocenter.io</sys_updated_by><sys_updated_on>2018-09-18 07:47:14</sys_updated_on><title/><width>container</width></sp_container></record_update>]]></payload>
        <payload_hash>-814769734</payload_hash>
        <record_name>VCM Home Page - Container 2</record_name>
        <reverted_from/>
        <source>92199c72db2caf40c203a2364b961980</source>
        <source_table>sys_update_set</source_table>
        <state>previous</state>
        <sys_created_by>Nehal.Ranpise@infocenter.io</sys_created_by>
        <sys_created_on>2018-09-18 07:47:14</sys_created_on>
        <sys_id>758178f6db6caf40c203a2364b961911</sys_id>
        <sys_mod_count>0</sys_mod_count>
        <sys_recorded_at>165eba5c4d30000001</sys_recorded_at>
        <sys_updated_by>Nehal.Ranpise@infocenter.io</sys_updated_by>
        <sys_updated_on>2018-09-18 07:47:14</sys_updated_on>
        <type>Container</type>
        <update_guid>7d8178f62c6caf4068b090ec8334dd10</update_guid>
        <update_guid_history>7d8178f62c6caf4068b090ec8334dd10:-814769734</update_guid_history>
    </sys_update_version>
    <sys_metadata_delete action="INSERT_OR_UPDATE">
        <sys_audit_delete display_value="Record deleted 2018-09-20 05:25:07">1f1bd7dbdb242380c203a2364b96191f</sys_audit_delete>
        <sys_class_name>sys_metadata_delete</sys_class_name>
        <sys_created_by>satej.kalyani@infocenter.io</sys_created_by>
        <sys_created_on>2018-09-20 09:25:07</sys_created_on>
        <sys_customer_update>false</sys_customer_update>
        <sys_db_object display_value="" name="sp_container">sp_container</sys_db_object>
        <sys_id>b28f3f13e2164058929cd69e72d7de90</sys_id>
        <sys_metadata>b18178f6db6caf40c203a2364b961910</sys_metadata>
        <sys_mod_count>0</sys_mod_count>
        <sys_name>VCM Home Page - Container 2</sys_name>
        <sys_package display_value="Vendor Contract Management" source="x_icir_vcm">3fe81872db2caf40c203a2364b9619e0</sys_package>
        <sys_parent/>
        <sys_policy/>
        <sys_replace_on_upgrade>false</sys_replace_on_upgrade>
        <sys_scope display_value="Vendor Contract Management">3fe81872db2caf40c203a2364b9619e0</sys_scope>
        <sys_scope_delete display_value="">10f7e6901f8f47e69075d98c142de984</sys_scope_delete>
        <sys_update_name>sp_container_b18178f6db6caf40c203a2364b961910</sys_update_name>
        <sys_update_version display_value="sp_container_b18178f6db6caf40c203a2364b961910">758178f6db6caf40c203a2364b961911</sys_update_version>
        <sys_updated_by>satej.kalyani@infocenter.io</sys_updated_by>
        <sys_updated_on>2018-09-20 09:25:07</sys_updated_on>
    </sys_metadata_delete>
</record_update>
